onig/__init__.py
onig/_encoding.py
onig/_onig_cffi/__init__.py
onig/_onig_cffi/build.py
onig/_onig_cffi/definitions.c
onig/_onig_cffi/source.c
onig/match.py
onig/pattern.py
onig/py.typed
onig/match.py
onig/pattern.py
onig/py.typed
onig/_encoding.py
onig/__init__.py
onig/_onig_cffi/build.py
onig/_onig_cffi/definitions.c
onig/_onig_cffi/source.c
onig/_onig_cffi/_onig_cffi.cp38-win_amd64.pyd
onig/_onig_cffi/__init__.py
onig-0.0.7.dist-info/WHEEL
onig-0.0.7.dist-info/METADATA
onig-0.0.7.dist-info/RECORD
